{"c34019cfdb022dc9895de1529f785285e8f0e061b4bc9d823244ab0dfc1a75fa":{"email":"test@example.com","formData":{"vorname":"Test"},"createdAt":"2025-11-05T16:16:31.640Z","verified":true},"66484bef3a1c1b380bc000518332d822731082bc3fe6a15b7eab1dcd7295aadd":{"email":"info@consulting-smc.de","formData":{"anrede":"herr","vorname":"Simon","nachname":"Müller","geburtsdatum":"2007-11-07","geburtsort":"Berlin","familienstand":"verheiratet","staatsangehoerigkeit":"deutsch","email":"info@consulting-smc.de","telefon":"01735608831","strasse":"Bissinger Str. ","hausnummer":"27","plz":"73252","ort":"Lenningen","produktKategorie":"privatkredit","kreditart":"autokredit","kreditsumme":"1000","laufzeit":"48","gewuenschteRate":"1000","verwendungszweck":"auto","baufinanzierungArt":"kauf","kaufpreisBaukosten":"","eigenkapital":"","beschaeftigungsverhaeltnis":"angestellt","nettoEinkommen":"","beschaeftigtSeit":"","miete":"400","sonstigeAusgaben":"","bestehendeDarlehen":"","bemerkungen":"","datenschutz":true,"newsletter":true,"gehaltsabrechnung1":null,"gehaltsabrechnung2":null,"gehaltsabrechnung3":null,"steuerbescheid1":null,"steuerbescheid2":null,"steuerbescheid3":null,"bwaGuV":null,"bestehendeKredite":null,"kontoauszug":null,"meldebescheinigung":null,"jahreskontoauszug":null,"baufinanzierungNachweis":null,"expose":null,"hatBestehendeKredite":true,"hatBaufinanzierung":false,"objektart":"","baujahr":"","grundstuecksgroesse":"","wohnflaeche":"","kaufpreis":"","modernisierungen":""},"createdAt":"2025-11-12T15:05:58.862Z","verified":false},"ac9f57fe893cdc521f372c842b0f19d827810abc6e988bf32649548eed4bb946":{"email":"info@consulting-smc.de","formData":{"anrede":"herr","vorname":"Simon","nachname":"Müller","geburtsdatum":"1992-09-26","geburtsort":"Montevideo","familienstand":"verheiratet","staatsangehoerigkeit":"albanisch","email":"info@consulting-smc.de","telefon":"01735608831","strasse":"Bissinger Str. ","hausnummer":"27","plz":"73252","ort":"Lenningen","produktKategorie":"privatkredit","kreditart":"ratenkredit","kreditsumme":"25000","laufzeit":"48","gewuenschteRate":"400","verwendungszweck":"auto","baufinanzierungArt":"","kaufpreisBaukosten":"","eigenkapital":"","beschaeftigungsverhaeltnis":"selbstständig","nettoEinkommen":"","beschaeftigtSeit":"","miete":"1000","sonstigeAusgaben":"","bestehendeDarlehen":"","bemerkungen":"","datenschutz":true,"newsletter":true,"gehaltsabrechnung1":null,"gehaltsabrechnung2":null,"gehaltsabrechnung3":null,"steuerbescheid1":null,"steuerbescheid2":null,"steuerbescheid3":null,"bwaGuV":null,"bestehendeKredite":null,"kontoauszug":null,"meldebescheinigung":null,"jahreskontoauszug":null,"baufinanzierungNachweis":null,"expose":null,"hatBestehendeKredite":true,"hatBaufinanzierung":false,"objektart":"","baujahr":"","grundstuecksgroesse":"","wohnflaeche":"","kaufpreis":"","modernisierungen":""},"createdAt":"2025-11-12T16:00:26.098Z","verified":false},"61d98fa1bbcc3bbb1360ed856982941e3a6fed9db3c382675cc1d1b7d798d6bb":{"email":"info@consulting-smc.de","formData":{"anrede":"herr","vorname":"Simon","nachname":"Müller","geburtsdatum":"1992-09-26","geburtsort":"montevideo","familienstand":"verheiratet","staatsangehoerigkeit":"deutsch","email":"info@consulting-smc.de","telefon":"01735608331","strasse":"Bissinger Str.","hausnummer":"27","plz":"73252","ort":"Lenningen","produktKategorie":"privatkredit","kreditart":"ratenkredit","kreditsumme":"25000","laufzeit":"48","gewuenschteRate":"300","verwendungszweck":"auto","baufinanzierungArt":"","kaufpreisBaukosten":"","eigenkapital":"","beschaeftigungsverhaeltnis":"selbstständig","nettoEinkommen":"","beschaeftigtSeit":"","miete":"690","sonstigeAusgaben":"","bestehendeDarlehen":"","bemerkungen":"","datenschutz":true,"newsletter":true,"gehaltsabrechnung1":null,"gehaltsabrechnung2":null,"gehaltsabrechnung3":null,"steuerbescheid1":null,"steuerbescheid2":null,"steuerbescheid3":null,"bwaGuV":null,"bestehendeKredite":null,"kontoauszug":null,"meldebescheinigung":null,"jahreskontoauszug":null,"baufinanzierungNachweis":null,"expose":null,"additionalDocuments":[],"hatBestehendeKredite":true,"hatBaufinanzierung":false,"objektart":"","baujahr":"","grundstuecksgroesse":"","wohnflaeche":"","kaufpreis":"","modernisierungen":""},"createdAt":"2025-11-12T16:05:07.005Z","verified":false}}